lmcp_tool_builder/__init__.py
lmcp_tool_builder/builder.py
lmcp_tool_builder/cli.py
lmcp_tool_builder-0.1.0.dist-info/licenses/LICENSE
lmcp_tool_builder-0.1.0.dist-info/METADATA
lmcp_tool_builder-0.1.0.dist-info/WHEEL
lmcp_tool_builder-0.1.0.dist-info/entry_points.txt
lmcp_tool_builder-0.1.0.dist-info/top_level.txt
lmcp_tool_builder-0.1.0.dist-info/RECORD
