Metadata-Version: 2.4
Name: lmcp-tool-builder
Version: 0.1.0
Summary: LMCP Tool Builder - 简化 LangChain 工具加载和集成
Home-page: https://github.com/lmcp-dev/lmcp-tool-builder
Author: LMCP Team
Author-email: LMCP Team <support@lmcp.dev>
License: MIT
Project-URL: Homepage, https://github.com/lmcp-dev/lmcp-tool-builder
Project-URL: Documentation, https://lmcp.dev/docs/tool-builder
Project-URL: Repository, https://github.com/lmcp-dev/lmcp-tool-builder
Project-URL: Issues, https://github.com/lmcp-dev/lmcp-tool-builder/issues
Keywords: lmcp,langchain,tools,ai,llm,agent,tool-builder,tool-management
Classifier: Development Status :: 4 - Beta
Classifier: Intended Audience :: Developers
Classifier: Topic :: Software Development :: Libraries :: Python Modules
Classifier: License :: OSI Approved :: MIT License
Classifier: Programming Language :: Python :: 3
Classifier: Programming Language :: Python :: 3.8
Classifier: Programming Language :: Python :: 3.9
Classifier: Programming Language :: Python :: 3.10
Classifier: Programming Language :: Python :: 3.11
Classifier: Programming Language :: Python :: 3.12
Classifier: Operating System :: OS Independent
Requires-Python: >=3.8
License-File: LICENSE
Requires-Dist: requests>=2.28.0
Provides-Extra: dev
Requires-Dist: pytest>=7.0.0; extra == "dev"
Requires-Dist: pytest-cov>=4.0.0; extra == "dev"
Requires-Dist: black>=23.0.0; extra == "dev"
Requires-Dist: flake8>=6.0.0; extra == "dev"
Requires-Dist: mypy>=1.0.0; extra == "dev"
Requires-Dist: twine>=4.0.0; extra == "dev"
Requires-Dist: build>=0.10.0; extra == "dev"
Provides-Extra: langchain
Requires-Dist: langchain>=0.1.0; extra == "langchain"
Requires-Dist: langchain-openai>=0.0.1; extra == "langchain"
Dynamic: author
Dynamic: home-page
Dynamic: license-file
Dynamic: requires-python
